{
  "artists": [
    {
      "id": "ting-ting-gao",
      "name": "Sophia Gao",
      "thumbnailImage": "https://raw.githubusercontent.com/StoryBeeBooks/oroaquae/main/Sophia%20Gao/Mist%20%EF%BC%88%E6%B0%A4%E6%B0%B2%EF%BC%89%20Series%20%239%20Oil%20on%20Canvas%2060_%20x%2048_%202018%20Commission%20Work%20SOLD.jpg",
      "biography": "<p>Sophia Gao is a contemporary artist whose work explores the intersection of traditional Chinese aesthetics and modern urban experiences. Gao's practice spans painting, mixed media, and installation art.</p><p>Her distinctive visual language combines delicate brushwork with bold compositional structures, creating works that bridge Eastern and Western artistic traditions. Through her art, Gao investigates themes of cultural identity, memory, and transformation in an increasingly globalized world.</p><p>Gao has exhibited internationally and her works are held in private collections across North America and Asia. She currently lives and works in Vancouver, Canada.</p>",
      "artworks": [
        {
          "title": "Comet",
          "year": "2015",
          "medium": "Mixed Media on Canvas",
          "dimensions": "12 x 12 inches",
          "image": "https://raw.githubusercontent.com/StoryBeeBooks/oroaquae/main/Sophia%20Gao/Comet%20Mixed%20Media%20on%20Canvas%2012%2012%202015%20SOLD.jpg"
        },
        {
          "title": "Unlimited No. 6",
          "year": "2016",
          "medium": "Oil on Canvas",
          "dimensions": "30 x 40 inches",
          "image": "https://raw.githubusercontent.com/StoryBeeBooks/oroaquae/main/Sophia%20Gao/Unlimited%20No.%206%20Oil%20on%20Canvas%2030_%20x%2040_%202016.jpg"
        },
        {
          "title": "Coral Sea No.1",
          "year": "2017",
          "medium": "Oil, Acrylic and Flower on Canvas",
          "dimensions": "24 x 30 inches",
          "image": "https://raw.githubusercontent.com/StoryBeeBooks/oroaquae/main/Sophia%20Gao/Coral%20Sea%20No.1%20Oil%2C%20Acrylic%20and%20Flower%20on%20Canvas%2024_%20x%2030_%202017%20SOLD.jpg"
        },
        {
          "title": "Coral Sea No.2",
          "year": "2017",
          "medium": "Acrylic on Canvas",
          "dimensions": "24 x 30 inches",
          "image": "https://raw.githubusercontent.com/StoryBeeBooks/oroaquae/main/Sophia%20Gao/Coral%20Sea%20No.2%20Acrylic%20on%20Canvas%2024_%20x%2030_%202017.jpg"
        },
        {
          "title": "Coral Sea No.3",
          "year": "2017",
          "medium": "Oil and Acrylic on Canvas",
          "dimensions": "24 x 30 inches",
          "image": "https://raw.githubusercontent.com/StoryBeeBooks/oroaquae/main/Sophia%20Gao/Coral%20Sea%20No.3%20Oil%20and%20Acrylic%20on%20Canvas%2024_%20x%2030_%202017%20SOLD.jpg"
        },
        {
          "title": "Flower on the Sea Series #18",
          "year": "2017",
          "medium": "Oil on Canvas",
          "dimensions": "12 x 24 inches",
          "image": "https://raw.githubusercontent.com/StoryBeeBooks/oroaquae/main/Sophia%20Gao/Flower%20on%20the%20Sea%20Series%20%2318%20Oil%20on%20Canvas%2012_%20x%2024_%202017%20Commission%20Work%20SOLD.jpg"
        },
        {
          "title": "Mist （氤氲） Series #5",
          "year": "2017",
          "medium": "Oil on Canvas",
          "dimensions": "24 x 12 inches",
          "image": "https://raw.githubusercontent.com/StoryBeeBooks/oroaquae/main/Sophia%20Gao/Mist%20%EF%BC%88%E6%B0%A4%E6%B0%B2%EF%BC%89%20Series%20%235%20Oil%20on%20Canvas%2024_%20x%2012_%202017.jpg"
        },
        {
          "title": "Soul's Pilgrimage II",
          "year": "2017",
          "medium": "Acrylic and Gold Leaf on Canvas",
          "dimensions": "60 x 36 inches",
          "image": "https://raw.githubusercontent.com/StoryBeeBooks/oroaquae/main/Sophia%20Gao/Soul_s%20Pilgrimage%20II%20Acrylic%20and%20Gold%20Leaf%20on%20Canvas%2060_%20x%2036_%202017%20SOLD.jpg"
        },
        {
          "title": "Wave",
          "year": "2017",
          "medium": "Resin, Acrylic on Wood Panel",
          "dimensions": "12 x 12 inches",
          "image": "https://raw.githubusercontent.com/StoryBeeBooks/oroaquae/main/Sophia%20Gao/Wave%20Resin%EF%BC%8CAcrylic%20on%20Wood%20Panel%2C%2012_%20x%2012_%202017%20SOLD.jpg"
        },
        {
          "title": "Mist （氤氲） Series #9",
          "year": "2018",
          "medium": "Oil on Canvas",
          "dimensions": "60 x 48 inches",
          "image": "https://raw.githubusercontent.com/StoryBeeBooks/oroaquae/main/Sophia%20Gao/Mist%20%EF%BC%88%E6%B0%A4%E6%B0%B2%EF%BC%89%20Series%20%239%20Oil%20on%20Canvas%2060_%20x%2048_%202018%20Commission%20Work%20SOLD.jpg"
        },
        {
          "title": "Concept No.263",
          "year": "2019",
          "medium": "Oil on Canvas",
          "dimensions": "48 x 72 inches",
          "image": "https://raw.githubusercontent.com/StoryBeeBooks/oroaquae/main/Sophia%20Gao/Concept%20No.263%20Oil%20on%20Canvas%204872_%202019.jpg"
        },
        {
          "title": "Coral Sea No.5",
          "year": "2019",
          "medium": "Acrylic on Canvas",
          "dimensions": "18 x 48 inches",
          "image": "https://raw.githubusercontent.com/StoryBeeBooks/oroaquae/main/Sophia%20Gao/Coral%20Sea%20No.5%20Acrylic%20on%20Canvas%2018_%20x%2048_%202019.jpg"
        },
        {
          "title": "Serenity",
          "year": "2019",
          "medium": "Oil and Acrylic on Canvas",
          "dimensions": "24 x 36 inches",
          "image": "https://raw.githubusercontent.com/StoryBeeBooks/oroaquae/main/Sophia%20Gao/Serenity%20Oil%20and%20Acrylic%20on%20Canvas%2024_%20%2036_%202019%20SOLD.jpg"
        },
        {
          "title": "Yellow Rhythm Series 5",
          "year": "2019",
          "medium": "Oil on Canvas",
          "dimensions": "24 x 36 inches",
          "image": "https://raw.githubusercontent.com/StoryBeeBooks/oroaquae/main/Sophia%20Gao/Yellow%20Rhythm%20Series%205%20Oil%20on%20Canvas%202436%202019.jpg"
        }
      ]
    },
    {
      "id": "susan-g-scott",
      "name": "Susan G. Scott",
      "thumbnailImage": "Susan G. Scott/SusanScott1.jpg",
      "biography": "<p>Susan G. Scott is a multidisciplinary artist whose practice encompasses sculpture, installation, and performance art. Scott has spent over three decades developing a unique artistic voice that challenges conventional notions of space, materiality, and viewer engagement.</p><p>Her work is characterized by an exploration of organic forms and natural materials, often creating immersive environments that invite contemplation and sensory experience. Scott's sculptures balance delicacy and strength, ephemeral and permanent, creating dialogues between opposing forces.</p><p>Scott has received numerous awards and grants, and her work has been exhibited in major galleries and museums internationally. She is based in Toronto, Canada.</p>",
      "artworks": [
        {
          "title": "Organic Form I",
          "year": "2023",
          "medium": "Sculpture",
          "dimensions": "Variable",
          "image": "Susan G. Scott/SusanScott1.jpg"
        },
        {
          "title": "Installation Series",
          "year": "2023",
          "medium": "Mixed media",
          "dimensions": "Variable",
          "image": "Susan G. Scott/SusanScott2.jpg"
        },
        {
          "title": "Natural Elements",
          "year": "2024",
          "medium": "Sculpture",
          "dimensions": "Variable",
          "image": "Susan G. Scott/SusanScott4.jpg"
        },
        {
          "title": "Ephemeral Structures",
          "year": "2024",
          "medium": "Installation",
          "dimensions": "Variable",
          "image": "Susan G. Scott/SusanScott6.jpg"
        },
        {
          "title": "Balance",
          "year": "2023",
          "medium": "Sculpture",
          "dimensions": "Variable",
          "image": "Susan G. Scott/SusanScott8.jpg"
        },
        {
          "title": "Dialogue",
          "year": "2024",
          "medium": "Mixed media",
          "dimensions": "Variable",
          "image": "Susan G. Scott/SusanScott9.jpg"
        }
      ]
    },
    {
      "id": "shelley-adler",
      "name": "Shelley Adler",
      "thumbnailImage": "Shelley Adler/ShelleyAdler1.jpg",
      "biography": "<p>Shelley Adler is a contemporary painter known for her vibrant, emotionally charged canvases that explore themes of identity, femininity, and psychological landscapes. Adler's work has evolved from figurative expressionism to increasingly abstract compositions.</p><p>Her paintings are distinguished by bold color palettes and gestural mark-making, creating dynamic surfaces that pulse with energy. Adler's practice is deeply introspective, drawing from personal experience while addressing universal themes of human connection and isolation.</p><p>Adler holds an MFA from Emily Carr University and has exhibited extensively throughout Canada and the United States. She maintains her studio practice in Vancouver.</p>",
      "artworks": [
        {
          "title": "Fluid Expressions I",
          "year": "2023",
          "medium": "Acrylic on canvas",
          "dimensions": "48 x 60 inches",
          "image": "Shelley Adler/ShelleyAdler1.jpg"
        },
        {
          "title": "Abstract Emotions",
          "year": "2023",
          "medium": "Mixed media on canvas",
          "dimensions": "36 x 48 inches",
          "image": "Shelley Adler/ShelleyAdler2.jpg"
        },
        {
          "title": "Color Study No. 5",
          "year": "2024",
          "medium": "Oil on canvas",
          "dimensions": "40 x 52 inches",
          "image": "Shelley Adler/ShelleyAdler3.jpg"
        },
        {
          "title": "Psychological Landscape",
          "year": "2024",
          "medium": "Acrylic and ink on canvas",
          "dimensions": "60 x 72 inches",
          "image": "Shelley Adler/ShelleyAdler4.jpg"
        },
        {
          "title": "Inner Dialogue",
          "year": "2023",
          "medium": "Oil on linen",
          "dimensions": "30 x 40 inches",
          "image": "Shelley Adler/ShelleyAdler5.jpg"
        },
        {
          "title": "Gestural Composition",
          "year": "2024",
          "medium": "Acrylic on canvas",
          "dimensions": "54 x 66 inches",
          "image": "Shelley Adler/ShelleyAdler6.jpg"
        }
      ]
    },
    {
      "id": "christine-reimer",
      "name": "Christine Reimer",
      "thumbnailImage": "Christine Reimer/ChristineReimer1.jpg",
      "biography": "<p>Christine Reimer is a conceptual artist whose interdisciplinary practice investigates the relationship between language, image, and meaning. Reimer works across photography, text-based art, installation, and video.</p><p>Her work often employs systems of classification and archival methods to examine how we construct narratives and preserve memory. Through meticulous research and careful formal considerations, Reimer creates works that are both intellectually rigorous and visually compelling.</p><p>Reimer has exhibited nationally and internationally, with works in numerous public and private collections. She is a Professor of Art at a leading Canadian university and maintains an active studio practice in Calgary.</p>",
      "artworks": [
        {
          "title": "Archival Studies I",
          "year": "2023",
          "medium": "Photography and text",
          "dimensions": "Variable",
          "image": "Christine Reimer/ChristineReimer1.jpg"
        },
        {
          "title": "Memory Systems",
          "year": "2023",
          "medium": "Mixed media installation",
          "dimensions": "Variable",
          "image": "Christine Reimer/ChristineReimer2.jpg"
        },
        {
          "title": "Classification Series No. 3",
          "year": "2024",
          "medium": "Photography",
          "dimensions": "30 x 40 inches",
          "image": "Christine Reimer/ChristineReimer3.jpg"
        },
        {
          "title": "Narrative Construction",
          "year": "2024",
          "medium": "Text and image",
          "dimensions": "Variable",
          "image": "Christine Reimer/ChristineReimer4.jpg"
        },
        {
          "title": "Documentary Evidence",
          "year": "2023",
          "medium": "Photography",
          "dimensions": "24 x 36 inches",
          "image": "Christine Reimer/ChristineReimer5.jpg"
        },
        {
          "title": "Language and Meaning",
          "year": "2024",
          "medium": "Installation",
          "dimensions": "Variable",
          "image": "Christine Reimer/ChristineReimer6.jpg"
        },
        {
          "title": "Preservation Study",
          "year": "2024",
          "medium": "Mixed media",
          "dimensions": "48 x 60 inches",
          "image": "Christine Reimer/ChristineReimer7.jpg"
        }
      ]
    },
    {
      "id": "leonel-jules",
      "name": "Leonel Jules",
      "thumbnailImage": "Leonel Jules/LeonelJules1.jpg",
      "biography": "<p>Leonel Jules is a contemporary artist whose practice explores issues of diaspora, cultural hybridity, and postcolonial identity. Jules immigrated to Canada from Haiti as a young adult, and this experience of migration profoundly informs his artistic vision.</p><p>Working primarily in painting and collage, Jules creates layered compositions that incorporate imagery from Caribbean history, popular culture, and personal memory. His works are vibrant celebrations of Afro-Caribbean culture while also addressing complex questions of belonging and representation.</p><p>Jules has received critical acclaim for his exhibitions across North America and his work is included in several museum collections. He lives and works in Montreal.</p>",
      "artworks": [
        {
          "title": "Diaspora Dreams",
          "year": "2023",
          "medium": "Mixed media and collage on canvas",
          "dimensions": "48 x 60 inches",
          "image": "Leonel Jules/LeonelJules1.jpg"
        },
        {
          "title": "Cultural Memory",
          "year": "2023",
          "medium": "Acrylic and collage on canvas",
          "dimensions": "36 x 48 inches",
          "image": "Leonel Jules/LeonelJules2.jpg"
        },
        {
          "title": "Caribbean Fragments",
          "year": "2024",
          "medium": "Mixed media on canvas",
          "dimensions": "40 x 52 inches",
          "image": "Leonel Jules/LeonelJules3.jpg"
        },
        {
          "title": "Hybrid Identity",
          "year": "2024",
          "medium": "Collage and painting",
          "dimensions": "54 x 66 inches",
          "image": "Leonel Jules/LeonelJules4.jpg"
        },
        {
          "title": "Postcolonial Narrative",
          "year": "2023",
          "medium": "Mixed media on canvas",
          "dimensions": "30 x 40 inches",
          "image": "Leonel Jules/LeonelJules5.jpg"
        },
        {
          "title": "Belonging",
          "year": "2024",
          "medium": "Acrylic and collage",
          "dimensions": "48 x 60 inches",
          "image": "Leonel Jules/LeonelJules6.jpg"
        },
        {
          "title": "Migration Stories",
          "year": "2024",
          "medium": "Mixed media on canvas",
          "dimensions": "42 x 54 inches",
          "image": "Leonel Jules/LeonelJules7.jpg"
        },
        {
          "title": "Cultural Celebration",
          "year": "2023",
          "medium": "Collage and painting",
          "dimensions": "36 x 48 inches",
          "image": "Leonel Jules/LeonelJules8.jpg"
        },
        {
          "title": "Afro-Caribbean Heritage",
          "year": "2024",
          "medium": "Mixed media on canvas",
          "dimensions": "60 x 72 inches",
          "image": "Leonel Jules/LeonelJules9.jpg"
        }
      ]
    },
    {
      "id": "andy-dixon",
      "name": "Andy Dixon",
      "thumbnailImage": "Andy Dixon/andydixon1.jpg",
      "biography": "<p>Andy Dixon is a painter and sculptor known for his darkly humorous take on consumer culture, celebrity, and the art world itself. Dixon's practice is characterized by technical virtuosity combined with a punk sensibility and irreverent wit.</p><p>His paintings often reference art historical traditions while subverting them through contemporary subject matter and bold compositional choices. Dixon's work has been described as both a critique and celebration of contemporary visual culture, navigating the space between high and low art with confidence and humor.</p><p>Dixon has exhibited internationally and his works are held in collections worldwide. He is based in Vancouver, where he maintains an active studio practice.</p>",
      "artworks": [
        {
          "title": "Consumer Culture I",
          "year": "2023",
          "medium": "Oil on canvas",
          "dimensions": "48 x 60 inches",
          "image": "Andy Dixon/andydixon1.jpg"
        },
        {
          "title": "Celebrity Study",
          "year": "2023",
          "medium": "Acrylic on canvas",
          "dimensions": "36 x 48 inches",
          "image": "Andy Dixon/andydixon2.jpg"
        },
        {
          "title": "Art World Critique",
          "year": "2024",
          "medium": "Oil on linen",
          "dimensions": "40 x 52 inches",
          "image": "Andy Dixon/andydixon3.jpg"
        },
        {
          "title": "Contemporary Irony",
          "year": "2024",
          "medium": "Mixed media on canvas",
          "dimensions": "54 x 66 inches",
          "image": "Andy Dixon/andydixon4.jpg"
        },
        {
          "title": "High/Low",
          "year": "2023",
          "medium": "Oil on canvas",
          "dimensions": "30 x 40 inches",
          "image": "Andy Dixon/andydixon5.jpg"
        },
        {
          "title": "Visual Culture",
          "year": "2024",
          "medium": "Acrylic and oil on canvas",
          "dimensions": "48 x 60 inches",
          "image": "Andy Dixon/andydixon6.jpg"
        },
        {
          "title": "Punk Aesthetics",
          "year": "2024",
          "medium": "Oil on canvas",
          "dimensions": "42 x 54 inches",
          "image": "Andy Dixon/andydixon7.jpg"
        },
        {
          "title": "Art Historical Reference",
          "year": "2023",
          "medium": "Mixed media on canvas",
          "dimensions": "60 x 72 inches",
          "image": "Andy Dixon/andydixon8.jpg"
        }
      ]
    },
    {
      "id": "ben-walmsley",
      "name": "Ben Walmsley",
      "thumbnailImage": "Ben Walmsley/BenWalmsley1.jpg",
      "biography": "<p>Ben Walmsley is an emerging artist whose practice centers on landscape painting and environmental awareness. Walmsley brings a contemporary perspective to the Canadian landscape tradition, addressing themes of climate change and human impact on natural environments.</p><p>His paintings are notable for their atmospheric quality and subtle color harmonies, evoking both the beauty and fragility of wilderness spaces. Walmsley's work invites viewers to consider their relationship with nature and the urgent need for environmental stewardship.</p><p>Walmsley has rapidly gained recognition in the Canadian art scene and has participated in numerous group and solo exhibitions. He works from his studio in British Columbia, drawing inspiration from the surrounding forests and coastlines.</p>",
      "artworks": [
        {
          "title": "Coastal Wilderness",
          "year": "2023",
          "medium": "Oil on canvas",
          "dimensions": "48 x 60 inches",
          "image": "Ben Walmsley/BenWalmsley1.jpg"
        },
        {
          "title": "Forest Study I",
          "year": "2023",
          "medium": "Acrylic on canvas",
          "dimensions": "36 x 48 inches",
          "image": "Ben Walmsley/BenWalmsley2.jpg"
        },
        {
          "title": "Climate Reflection",
          "year": "2024",
          "medium": "Oil on linen",
          "dimensions": "40 x 52 inches",
          "image": "Ben Walmsley/BenWalmsley3.jpg"
        },
        {
          "title": "Atmospheric Landscape",
          "year": "2024",
          "medium": "Oil on canvas",
          "dimensions": "54 x 66 inches",
          "image": "Ben Walmsley/BenWalmsley4.jpg"
        },
        {
          "title": "Fragile Beauty",
          "year": "2023",
          "medium": "Acrylic on canvas",
          "dimensions": "30 x 40 inches",
          "image": "Ben Walmsley/BenWalmsley5.jpg"
        },
        {
          "title": "Environmental Awareness",
          "year": "2024",
          "medium": "Oil on canvas",
          "dimensions": "48 x 60 inches",
          "image": "Ben Walmsley/BenWalmsley6.jpg"
        },
        {
          "title": "BC Coastline",
          "year": "2024",
          "medium": "Oil on linen",
          "dimensions": "42 x 54 inches",
          "image": "Ben Walmsley/BenWalmsley7.jpg"
        },
        {
          "title": "Wilderness Preservation",
          "year": "2023",
          "medium": "Acrylic on canvas",
          "dimensions": "60 x 72 inches",
          "image": "Ben Walmsley/BenWalmsley8.jpg"
        }
      ]
    }
  ]
}
